cjs_tutorial/__init__.py
cjs_tutorial/cli.py
cjs_tutorial/lib.py
cjs_tutorial/plot.py
cjs_tutorial-0.0.3.dist-info/entry_points.txt
cjs_tutorial-0.0.3.dist-info/LICENSE
cjs_tutorial-0.0.3.dist-info/WHEEL
cjs_tutorial-0.0.3.dist-info/METADATA
cjs_tutorial-0.0.3.dist-info/RECORD
